oxdomains/__init__.py
oxdomains/main.py
oxdomains-0.0.1.dist-info/METADATA
oxdomains-0.0.1.dist-info/WHEEL
oxdomains-0.0.1.dist-info/entry_points.txt
oxdomains-0.0.1.dist-info/top_level.txt
oxdomains-0.0.1.dist-info/RECORD
