Metadata-Version: 2.1
Name: oxdomains
Version: 0.0.1
Summary: A Handy Script for Finding Sub-Domains using google dorks and certspotter.com
Author: 0x68616469
Keywords: subdomains,google dorks,certification
Classifier: Development Status :: 4 - Beta
Classifier: Intended Audience :: Developers
Classifier: Programming Language :: Python :: 3
Classifier: Operating System :: Unix
Classifier: Operating System :: MacOS :: MacOS X
Classifier: Operating System :: Microsoft :: Windows
Requires-Dist: google
Requires-Dist: oxflags
Requires-Dist: oxansi
